hexopy/__init__.py
hexopy/cli.py
hexopy/command.py
hexopy/database.py
hexopy/manage.py
hexopy/paginate.py
hexopy/printer.py
hexopy/response.py
hexopy/server.py
hexopy/types.py
hexopy-0.2.1.dist-info/LICENSE
hexopy-0.2.1.dist-info/METADATA
hexopy-0.2.1.dist-info/WHEEL
hexopy-0.2.1.dist-info/entry_points.txt
hexopy-0.2.1.dist-info/top_level.txt
hexopy-0.2.1.dist-info/RECORD
