Metadata-Version: 2.2
Name: hexopy
Version: 0.2.1
Summary: HexOPy 🛠️🐍 – Hexagonal Architecture for Python
Author-email: Javier Avila njavilas <njavilas2015@gmail.com>
License: MIT License
Project-URL: Homepage, https://github.com/njavilas2015/HexOPy
Project-URL: Bug Tracker, https://github.com/njavilas2015/HexOPy/issues
Classifier: Programming Language :: Python :: 3
Classifier: License :: OSI Approved :: MIT License
Classifier: Operating System :: OS Independent
License-File: LICENSE
Requires-Dist: colorama==0.4.6
Requires-Dist: pydantic==2.10.6
Requires-Dist: pytest==8.3.4
Requires-Dist: asyncpg==0.30.0
Requires-Dist: uvicorn==0.34.0
Requires-Dist: aerich
Requires-Dist: tortoise-orm
Requires-Dist: aiosqlite
Requires-Dist: fastapi
